Pprints/Ppr_class.py
Pprints/__init__.py
bidi/__init__.py
bidi/algorithm.py
bidi/mirror.py
Pprints-2.0.0.dist-info/LICENSE
Pprints-2.0.0.dist-info/METADATA
Pprints-2.0.0.dist-info/WHEEL
Pprints-2.0.0.dist-info/top_level.txt
Pprints-2.0.0.dist-info/RECORD
