Metadata-Version: 2.1
Name: Pprints
Version: 2.0.0
Summary: A library for printing Persian text in color and without color (:
Home-page: https://github.com/aminrngbr1122
Author: Amin Rngbr
Author-email: rngbramin@gmail.com
License: MIT
Keywords: Print,print,persian,Persian,PP,iran,Iran,Arab,arab,jiji,ColorTER,Pprints,PPRINTs,PPrints
Platform: Windows
License-File: LICENSE
Requires-Dist: colorter
Requires-Dist: arabic-reshaper
